MANIFEST.in
README.rst
setup.cfg
setup.py
grg_grgdata/__init__.py
grg_grgdata/cmd.py
grg_grgdata/common.py
grg_grgdata/exception.py
grg_grgdata/io.py
grg_grgdata/struct.py
grg_grgdata.egg-info/PKG-INFO
grg_grgdata.egg-info/SOURCES.txt
grg_grgdata.egg-info/dependency_links.txt
grg_grgdata.egg-info/requires.txt
grg_grgdata.egg-info/top_level.txt
grg_grgdata/schema/GRGv1.0_schema.json
grg_grgdata/schema/GRGv1.5_schema.json
grg_grgdata/schema/GRGv1.6_schema.json
grg_grgdata/schema/GRGv2.0_schema.json
grg_grgdata/schema/GRGv3.0_schema.json
grg_grgdata/schema/GRGv4.0_schema.json
grg_grgdata/schema/GRGv4.1_schema.json